unboil_fastapi_auth/__init__.py
unboil_fastapi_auth/dependencies.py
unboil_fastapi_auth/models.py
unboil_fastapi_auth/routes.py
unboil_fastapi_auth/schemas.py
unboil_fastapi_auth/service.py
unboil_fastapi_auth/utils.py
unboil_fastapi_auth/providers/__init__.py
unboil_fastapi_auth/providers/email.py
unboil_fastapi_auth/providers/google.py
unboil_fastapi_auth-0.1.1.dist-info/METADATA
unboil_fastapi_auth-0.1.1.dist-info/WHEEL
unboil_fastapi_auth-0.1.1.dist-info/RECORD
