Metadata-Version: 2.4
Name: unboil-fastapi-auth
Version: 0.1.1
Summary: Add your description here
Author: eyueldk
Requires-Python: >=3.9
Requires-Dist: bcrypt>=4.0.0
Requires-Dist: fastapi>=0.100.0
Requires-Dist: google-api-python-client>=2.0.0
Requires-Dist: google-auth>=2.0.0
Requires-Dist: passlib>=1.0.0
Requires-Dist: pydantic>=2.0.0
Requires-Dist: sqlalchemy>=2.0.0
